dyndns/__init__.py
dyndns/command_line.py
dyndns/domain_setup.py
dyndns/domain_status.py
dyndns/domain_update.py
domain_connect_dyndns-0.0.4.dist-info/LICENSE
domain_connect_dyndns-0.0.4.dist-info/METADATA
domain_connect_dyndns-0.0.4.dist-info/WHEEL
domain_connect_dyndns-0.0.4.dist-info/entry_points.txt
domain_connect_dyndns-0.0.4.dist-info/top_level.txt
domain_connect_dyndns-0.0.4.dist-info/RECORD
