Metadata-Version: 2.1
Name: domain-connect-dyndns
Version: 0.0.4
Summary: Python client library for Dynamic DNS using Domain Connect
Home-page: https://github.com/Domain-Connect/DomainConnectDDNS-Python
Author: Andreea Dima
Author-email: andreea.dima@1and1.ro
License: MIT
Platform: UNKNOWN
Classifier: Programming Language :: Python :: 3
Classifier: Programming Language :: Python :: 2
Classifier: License :: OSI Approved :: MIT License
Classifier: Operating System :: OS Independent
Requires-Dist: validators (>=0.12.2)
Requires-Dist: requests (>=2.19.1)
Requires-Dist: dnspython (>=1.15.0)
Requires-Dist: domain-connect (>=0.0.6)
